utils_plus/__init__.py
utils_plus/decorator.py
utils_plus/decorators.py
utils_plus/parser.py
utils_plus/utility.py
utils_functions_plus-0.0.8.dist-info/LICENSE
utils_functions_plus-0.0.8.dist-info/METADATA
utils_functions_plus-0.0.8.dist-info/WHEEL
utils_functions_plus-0.0.8.dist-info/top_level.txt
utils_functions_plus-0.0.8.dist-info/RECORD
