Metadata-Version: 2.1
Name: utils-functions-plus
Version: 0.0.8
Summary: A set of auxiliary functions
Home-page: https://github.com/fabmax94/utils_plus
Author: Fabio Alexandre
Author-email: famhs@ecomp.poli.br
License: UNKNOWN
Platform: UNKNOWN
Classifier: Programming Language :: Python :: 3
Classifier: License :: OSI Approved :: MIT License
Classifier: Operating System :: OS Independent
Requires-Python: >=3.6
